pypfs/__init__.py
pypfs/client.py
pypfs/exceptions.py
pypfs/helpers.py
pypfs-0.1.2.dist-info/METADATA
pypfs-0.1.2.dist-info/WHEEL
pypfs-0.1.2.dist-info/RECORD
